smoltools/__init__.py
smoltools/calculate/__init__.py
smoltools/calculate/distance.py
smoltools/fret0/__init__.py
smoltools/fret0/efficiency.py
smoltools/fret0/main.py
smoltools/fret0/plots.py
smoltools/fret0/utils.py
smoltools/noesy_neighbors/__init__.py
smoltools/noesy_neighbors/main.py
smoltools/noesy_neighbors/plots.py
smoltools/noesy_neighbors/utils.py
smoltools/pdbtools/__init__.py
smoltools/pdbtools/coordinates.py
smoltools/pdbtools/exceptions.py
smoltools/pdbtools/load.py
smoltools/pdbtools/select.py
smoltools/pdbtools/utils.py
smoltools/rate_my_plate/__init__.py
smoltools/rate_my_plate/main.py
smoltools/rate_my_plate/plots.py
smoltools/resources/__init__.py
smoltools/resources/colors.py
smoltools-1.0.13.dist-info/LICENSE
smoltools-1.0.13.dist-info/METADATA
smoltools-1.0.13.dist-info/WHEEL
smoltools-1.0.13.dist-info/top_level.txt
smoltools-1.0.13.dist-info/RECORD
