Metadata-Version: 2.1
Name: smoltools
Version: 1.0.13
Summary: Collection of tools for various single-molecule experiments.
Home-page: https://github.com/AYSung/smoltools/
Author: Andrew Sung
Author-email: aysung300@gmail.com
Project-URL: Bug Tracker, https://github.com/AYSung/smoltools/issues
Classifier: Programming Language :: Python :: 3
Classifier: License :: OSI Approved :: MIT License
Classifier: Operating System :: OS Independent
Requires-Python: >=3.10.4
License-File: LICENSE
